odoo_connect/__init__.py
odoo_connect/data.py
odoo_connect/explore.py
odoo_connect/format.py
odoo_connect/odoo_rpc.py
odoo_connect/py.typed
odoo_connect-0.6.0.dist-info/licenses/LICENSE
odoo_connect-0.6.0.dist-info/METADATA
odoo_connect-0.6.0.dist-info/WHEEL
odoo_connect-0.6.0.dist-info/top_level.txt
odoo_connect-0.6.0.dist-info/RECORD
