Metadata-Version: 2.4
Name: odoo-connect
Version: 0.6.0
Summary: Simple RPC client for Odoo
Author-email: Krzysztof Magusiak <chrmag@poczta.onet.pl>
License:                    GNU LESSER GENERAL PUBLIC LICENSE
Project-URL: Homepage, https://github.com/kmagusiak/odoo-connect
Keywords: odoo,rpc
Classifier: Development Status :: 4 - Beta
Classifier: License :: OSI Approved :: GNU Lesser General Public License v3 (LGPLv3)
Classifier: Programming Language :: Python :: 3
Classifier: Framework :: Odoo
Requires-Python: >=3.9
License-File: LICENSE
Requires-Dist: requests
Provides-Extra: pinned
Requires-Dist: requests==2.32.3; extra == "pinned"
Requires-Dist: charset-normalizer==3.3.2; extra == "pinned"
Requires-Dist: idna==3.7; extra == "pinned"
Provides-Extra: dev
Requires-Dist: mypy~=1.11; extra == "dev"
Requires-Dist: ruff==0.5.6; extra == "dev"
Requires-Dist: types-requests~=2.31.0; extra == "dev"
Requires-Dist: ipython>=8; extra == "dev"
Provides-Extra: test
Requires-Dist: pytest==8.3.2; extra == "test"
Requires-Dist: pytest-httpserver==1.0.12; extra == "test"
Dynamic: license-file
